{
  "encounter": {
    "height": 44,
    "pixelRatio": 2,
    "width": 44,
    "x": 0,
    "y": 0
  },
  "encounter-highlight": {
    "height": 44,
    "pixelRatio": 2,
    "width": 44,
    "x": 44,
    "y": 0
  },
  "loitering": {
    "height": 44,
    "pixelRatio": 2,
    "width": 44,
    "x": 0,
    "y": 44
  },
  "loitering-highlight": {
    "height": 44,
    "pixelRatio": 2,
    "width": 44,
    "x": 44,
    "y": 44
  },
  "port": {
    "height": 44,
    "pixelRatio": 2,
    "width": 44,
    "x": 88,
    "y": 0
  },
  "port-highlight": {
    "height": 40,
    "pixelRatio": 2,
    "width": 40,
    "x": 132,
    "y": 0
  }
}